asqi/__init__.py
asqi/config.py
asqi/container_manager.py
asqi/datasets.py
asqi/errors.py
asqi/logging_config.py
asqi/main.py
asqi/metric_expression.py
asqi/output.py
asqi/rag_response_schema.py
asqi/response_schemas.py
asqi/schemas.py
asqi/score_card_engine.py
asqi/validation.py
asqi/workflow.py
asqi/schemas/asqi_datasets_config.schema.json
asqi/schemas/asqi_generation_config.schema.json
asqi/schemas/asqi_manifest.schema.json
asqi/schemas/asqi_score_card.schema.json
asqi/schemas/asqi_suite_config.schema.json
asqi/schemas/asqi_systems_config.schema.json
asqi_engineer-0.4.1.dist-info/METADATA
asqi_engineer-0.4.1.dist-info/WHEEL
asqi_engineer-0.4.1.dist-info/entry_points.txt
asqi_engineer-0.4.1.dist-info/licenses/LICENSE
asqi_engineer-0.4.1.dist-info/RECORD
