Metadata-Version: 2.4
Name: asqi-engineer
Version: 0.4.1
Summary: ASQI quality checks for AI systems
License-File: LICENSE
Requires-Python: >=3.12
Requires-Dist: datasets[vision]>=4.4.1
Requires-Dist: dbos[otel]==2.7.0
Requires-Dist: docker>=7.1.0
Requires-Dist: pydantic>=2.11.7
Requires-Dist: python-dotenv>=1.1.1
Requires-Dist: pyyaml>=6.0.2
Requires-Dist: rich>=14.1.0
Requires-Dist: typer>=0.16.0
Requires-Dist: urllib3>=2.6.3
